runtime/__init__.py
runtime/arc.py
runtime/config.py
runtime/py.typed
runtime/integrations/__init__.py
runtime/integrations/langgraph.py
runtime/interceptors/__init__.py
runtime/interceptors/base.py
runtime/interceptors/mcp.py
runtime/interceptors/openai.py
runtime/multiagent/__init__.py
runtime/multiagent/context.py
runtime/patterns/__init__.py
runtime/patterns/matcher.py
runtime/patterns/registry.py
runtime/proto/__init__.py
runtime/proto/telemetry.proto
runtime/proto/telemetry_pb2.py
runtime/proto/telemetry_pb2_grpc.py
runtime/telemetry/__init__.py
runtime/telemetry/client.py
runtime/telemetry/metrics.py
runtime/telemetry/metrics_server.py
runtime/telemetry/otel_client.py
arc_runtime-0.1.5.dist-info/METADATA
arc_runtime-0.1.5.dist-info/WHEEL
arc_runtime-0.1.5.dist-info/top_level.txt
arc_runtime-0.1.5.dist-info/RECORD
