Metadata-Version: 2.4
Name: arc-runtime
Version: 0.1.5
Summary: Lightweight Python interceptor that prevents AI agent failures in real-time
Author-email: "Arc Intelligence, Inc." <Jarrod@arc.computer>
Project-URL: Homepage, https://github.com/arc-computer/runtime
Project-URL: Documentation, https://github.com/arc-computer/runtime#readme
Project-URL: Bug Tracker, https://github.com/arc-computer/runtime/issues
Project-URL: Source Code, https://github.com/arc-computer/runtime
Keywords: ai,llm,openai,anthropic,reliability,monitoring,telemetry,interceptor
Classifier: Development Status :: 4 - Beta
Classifier: Intended Audience :: Developers
Classifier: License :: OSI Approved :: MIT License
Classifier: Programming Language :: Python :: 3
Classifier: Programming Language :: Python :: 3.8
Classifier: Programming Language :: Python :: 3.9
Classifier: Programming Language :: Python :: 3.10
Classifier: Programming Language :: Python :: 3.11
Classifier: Programming Language :: Python :: 3.12
Classifier: Programming Language :: Python :: 3.13
Classifier: Topic :: Software Development :: Libraries :: Python Modules
Classifier: Topic :: Scientific/Engineering :: Artificial Intelligence
Classifier: Operating System :: OS Independent
Classifier: Typing :: Typed
Requires-Python: >=3.8
Requires-Dist: wrapt>=1.14.0
Requires-Dist: grpcio>=1.50.0
Requires-Dist: protobuf<7.0.0,>=3.20.0
Requires-Dist: httpx>=0.25.0
Provides-Extra: telemetry
Requires-Dist: grpcio>=1.50.0; extra == "telemetry"
Requires-Dist: opentelemetry-api>=1.20.0; extra == "telemetry"
Requires-Dist: opentelemetry-sdk>=1.20.0; extra == "telemetry"
Requires-Dist: opentelemetry-instrumentation>=0.41b0; extra == "telemetry"
Provides-Extra: dev
Requires-Dist: pytest>=7.0.0; extra == "dev"
Requires-Dist: pytest-asyncio>=0.21.0; extra == "dev"
Requires-Dist: pytest-cov>=4.0.0; extra == "dev"
Requires-Dist: openai>=1.0.0; extra == "dev"
Requires-Dist: grpcio>=1.50.0; extra == "dev"
Requires-Dist: grpcio-tools>=1.50.0; extra == "dev"
Requires-Dist: twine>=4.0.0; extra == "dev"
Requires-Dist: wheel>=0.40.0; extra == "dev"
Requires-Dist: build>=0.10.0; extra == "dev"
